{
  "coord": {
    "lon": 0.2196,
    "lat": 51.4435
  },
  "weather": [
    {
      "id": 802,
      "main": "Clouds",
      "description": "scattered clouds",
      "icon": "03d"
    }
  ],
  "base": "stations",
  "main": {
    "temp": 15.64,
    "feels_like": 15.37,
    "temp_min": 15.12,
    "temp_max": 17.63,
    "pressure": 1025,
    "humidity": 81,
    "sea_level": 1025,
    "grnd_level": 1021
  },
  "visibility": 10000,
  "wind": {
    "speed": 1,
    "deg": 106,
    "gust": 1.29
  },
  "clouds": {
    "all": 39
  },
  "dt": 1784701628,
  "sys": {
    "type": 2,
    "id": 2011528,
    "country": "GB",
    "sunrise": 1784693303,
    "sunset": 1784750544
  },
  "timezone": 3600,
  "id": 2651500,
  "name": "Dartford",
  "cod": 200,
  "_last_updated_utc": "2026-07-22T06:28:25.223Z"
}