{
  "coord": {
    "lon": 0.2196,
    "lat": 51.4435
  },
  "weather": [
    {
      "id": 804,
      "main": "Clouds",
      "description": "overcast clouds",
      "icon": "04d"
    }
  ],
  "base": "stations",
  "main": {
    "temp": 23.54,
    "feels_like": 23.26,
    "temp_min": 22.8,
    "temp_max": 25.16,
    "pressure": 1020,
    "humidity": 50,
    "sea_level": 1020,
    "grnd_level": 1015
  },
  "visibility": 10000,
  "wind": {
    "speed": 2.24,
    "deg": 223,
    "gust": 5.36
  },
  "clouds": {
    "all": 95
  },
  "dt": 1782829219,
  "sys": {
    "type": 2,
    "id": 2011528,
    "country": "GB",
    "sunrise": 1782791143,
    "sunset": 1782850770
  },
  "timezone": 3600,
  "id": 2651500,
  "name": "Dartford",
  "cod": 200,
  "_last_updated_utc": "2026-06-30T14:20:19.601Z"
}