{
  "coord": {
    "lon": 0.2196,
    "lat": 51.4435
  },
  "weather": [
    {
      "id": 800,
      "main": "Clear",
      "description": "clear sky",
      "icon": "01d"
    }
  ],
  "base": "stations",
  "main": {
    "temp": 27.03,
    "feels_like": 28.99,
    "temp_min": 26.78,
    "temp_max": 28.49,
    "pressure": 1017,
    "humidity": 71,
    "sea_level": 1017,
    "grnd_level": 1012
  },
  "visibility": 10000,
  "wind": {
    "speed": 3.08,
    "deg": 2,
    "gust": 4.5
  },
  "clouds": {
    "all": 1
  },
  "dt": 1782286882,
  "sys": {
    "type": 2,
    "id": 20115,
    "country": "GB",
    "sunrise": 1782272570,
    "sunset": 1782332404
  },
  "timezone": 3600,
  "id": 2651500,
  "name": "Dartford",
  "cod": 200,
  "_last_updated_utc": "2026-06-24T07:41:22.074Z"
}